setl/__init__.py
setl/__main__.py
setl/_logging.py
setl/errs.py
setl/cmds/__init__.py
setl/cmds/_utils.py
setl/cmds/build.py
setl/cmds/clean.py
setl/cmds/develop.py
setl/cmds/publish.py
setl/cmds/setuppy.py
setl/projects/__init__.py
setl/projects/_envs.py
setl/projects/base.py
setl/projects/build.py
setl/projects/clean.py
setl/projects/dev.py
setl/projects/hook.py
setl/projects/meta.py
setl/projects/setup.py
setl-0.10.0.dist-info/METADATA
setl-0.10.0.dist-info/WHEEL
setl-0.10.0.dist-info/entry_points.txt
setl-0.10.0.dist-info/top_level.txt
setl-0.10.0.dist-info/zip-safe
setl-0.10.0.dist-info/RECORD
