Metadata-Version: 2.1
Name: setl
Version: 0.10.0
Summary: Packaging tool for PEP 518 projects with Setuptools backend.
Home-page: https://github.com/uranusjr/setl
Author: Tzu-ping Chung
Author-email: uranusjr@gmail.com
License: ISC
Project-URL: Documentation, https://setl.readthedocs.io
Project-URL: CI, https://travis-ci.com/uranusjr/setl
Platform: UNKNOWN
Classifier: Development Status :: 4 - Beta
Classifier: Environment :: Console
Classifier: Intended Audience :: Developers
Classifier: License :: OSI Approved :: ISC License (ISCL)
Classifier: Operating System :: OS Independent
Classifier: Programming Language :: Python :: 3 :: Only
Classifier: Programming Language :: Python :: 3.7
Classifier: Programming Language :: Python :: 3.8
Classifier: Programming Language :: Python :: 3.9
Classifier: Topic :: Software Development :: Build Tools
Classifier: Topic :: System :: Archiving :: Packaging
Classifier: Topic :: System :: Software Distribution
Classifier: Topic :: Utilities
Requires-Python: >=3.7
Requires-Dist: cached-property
Requires-Dist: packaging
Requires-Dist: pep517
Requires-Dist: toml
Requires-Dist: twine
Provides-Extra: docs
Requires-Dist: sphinx ; extra == 'docs'
Requires-Dist: sphinx-argparse ; extra == 'docs'
Requires-Dist: sphinx-rtd-theme ; extra == 'docs'
Provides-Extra: test
Requires-Dist: pytest ; extra == 'test'
